medimages4tests/__init__.py
medimages4tests/_version.py
medimages4tests/cache_dir.py
medimages4tests/import_tools.py
medimages4tests/utils.py
medimages4tests/dummy/__init__.py
medimages4tests/dummy/nifti.py
medimages4tests/dummy/dicom/__init__.py
medimages4tests/dummy/dicom/base.py
medimages4tests/dummy/dicom/ct/__init__.py
medimages4tests/dummy/dicom/ct/ac/__init__.py
medimages4tests/dummy/dicom/ct/ac/siemens/biograph_vision/__init__.py
medimages4tests/dummy/dicom/ct/ac/siemens/biograph_vision/vr20b.py
medimages4tests/dummy/dicom/ct/wholebody/__init__.py
medimages4tests/dummy/dicom/ct/wholebody/siemens/biograph_vision/__init__.py
medimages4tests/dummy/dicom/ct/wholebody/siemens/biograph_vision/vr20b.py
medimages4tests/dummy/dicom/mri/__init__.py
medimages4tests/dummy/dicom/mri/dwi/__init__.py
medimages4tests/dummy/dicom/mri/dwi/siemens/__init__.py
medimages4tests/dummy/dicom/mri/dwi/siemens/skyra/__init__.py
medimages4tests/dummy/dicom/mri/dwi/siemens/skyra/syngo_d13c.py
medimages4tests/dummy/dicom/mri/fmap/__init__.py
medimages4tests/dummy/dicom/mri/fmap/ge/discovery_mr888/__init__.py
medimages4tests/dummy/dicom/mri/fmap/ge/discovery_mr888/dv26_0_r05_2008a.py
medimages4tests/dummy/dicom/mri/fmap/siemens/__init__.py
medimages4tests/dummy/dicom/mri/fmap/siemens/skyra/__init__.py
medimages4tests/dummy/dicom/mri/fmap/siemens/skyra/syngo_d13c.py
medimages4tests/dummy/dicom/mri/t1w/siemens/skyra/syngo_d13c.py
medimages4tests/dummy/dicom/pet/__init__.py
medimages4tests/dummy/dicom/pet/statistics/siemens/__init__.py
medimages4tests/dummy/dicom/pet/statistics/siemens/biograph_vision/__init__.py
medimages4tests/dummy/dicom/pet/statistics/siemens/biograph_vision/vr20b.py
medimages4tests/dummy/dicom/pet/topogram/siemens/__init__.py
medimages4tests/dummy/dicom/pet/topogram/siemens/biograph_vision/__init__.py
medimages4tests/dummy/dicom/pet/topogram/siemens/biograph_vision/vr20b.py
medimages4tests/dummy/dicom/pet/uncorrected/siemens/__init__.py
medimages4tests-0.5.7.dist-info/licenses/LICENSE
medimages4tests-0.5.7.dist-info/METADATA
medimages4tests-0.5.7.dist-info/WHEEL
medimages4tests-0.5.7.dist-info/top_level.txt
medimages4tests-0.5.7.dist-info/RECORD
