Metadata-Version: 2.4
Name: medimages4tests
Version: 0.5.7
Summary: Generates dummy medical image data with realistic headers to be used in image handling tests
Home-page: https://github.com/australian-imaging-service/medimages4tests
Author: Thomas G. Close
Author-email: tom.g.close@gmail.com
License: CC0
Keywords: repository analysis medical-imaging neuroimaging workflows pipelines
Classifier: Development Status :: 4 - Beta
Classifier: Intended Audience :: Healthcare Industry
Classifier: Intended Audience :: Science/Research
Classifier: License :: OSI Approved :: Apache Software License
Classifier: Natural Language :: English
Classifier: Topic :: Scientific/Engineering :: Bio-Informatics
Classifier: Topic :: Scientific/Engineering :: Medical Science Apps.
Classifier: Programming Language :: Python :: 3.8
Classifier: Programming Language :: Python :: 3.9
Classifier: Programming Language :: Python :: 3.10
Classifier: Programming Language :: Python :: 3.11
Classifier: Programming Language :: Python :: 3.12
Classifier: Programming Language :: Python :: 3.13
License-File: LICENSE
Requires-Dist: pydicom>=2.4.4
Requires-Dist: nibabel>=4.0.1
Requires-Dist: openneuro-py>=2022.2.0
Requires-Dist: attrs>=21.4.0
Provides-Extra: test
Requires-Dist: pytest>=5.4.3; extra == "test"
Requires-Dist: pytest-env>=0.6.2; extra == "test"
Requires-Dist: pytest-cov>=2.12.1; extra == "test"
Dynamic: author
Dynamic: author-email
Dynamic: classifier
Dynamic: description
Dynamic: home-page
Dynamic: keywords
Dynamic: license
Dynamic: license-file
Dynamic: provides-extra
Dynamic: requires-dist
Dynamic: summary
